odoo/addons/repair_order_line_sequence/README.rst
odoo/addons/repair_order_line_sequence/__init__.py
odoo/addons/repair_order_line_sequence/__manifest__.py
odoo/addons/repair_order_line_sequence/i18n/it.po
odoo/addons/repair_order_line_sequence/i18n/repair_order_line_sequence.pot
odoo/addons/repair_order_line_sequence/readme/CONTEXT.md
odoo/addons/repair_order_line_sequence/readme/CONTRIBUTORS.md
odoo/addons/repair_order_line_sequence/readme/DESCRIPTION.md
odoo/addons/repair_order_line_sequence/readme/USAGE.md
odoo/addons/repair_order_line_sequence/readme/newsfragments/.gitkeep
odoo/addons/repair_order_line_sequence/static/description/icon.png
odoo/addons/repair_order_line_sequence/static/description/index.html
odoo/addons/repair_order_line_sequence/views/repair_order_views.xml
odoo_addon_repair_order_line_sequence-18.0.1.0.0.3.dist-info/METADATA
odoo_addon_repair_order_line_sequence-18.0.1.0.0.3.dist-info/WHEEL
odoo_addon_repair_order_line_sequence-18.0.1.0.0.3.dist-info/top_level.txt
odoo_addon_repair_order_line_sequence-18.0.1.0.0.3.dist-info/RECORD
